plotdetection/__init__.py
plotdetection/visualization.py
plotdetection-0.1.dist-info/METADATA
plotdetection-0.1.dist-info/WHEEL
plotdetection-0.1.dist-info/top_level.txt
plotdetection-0.1.dist-info/RECORD
